kirkwoodnight/__init__.py
kirkwoodnight/command_line.py
kirkwoodnight/plotting.py
kirkwoodnight/source.py
kirkwoodnight/data/obj_list.csv
kirkwoodnight-1.0.4.dist-info/LICENSE.txt
kirkwoodnight-1.0.4.dist-info/METADATA
kirkwoodnight-1.0.4.dist-info/WHEEL
kirkwoodnight-1.0.4.dist-info/entry_points.txt
kirkwoodnight-1.0.4.dist-info/top_level.txt
kirkwoodnight-1.0.4.dist-info/RECORD
