Metadata-Version: 2.1
Name: kirkwoodnight
Version: 1.0.4
Summary: Interactive command line tool to assist with observations at Kirkwood Observatory.
Home-page: http://packages.python.org/kirkwoodnight
Author: Armaan Goyal, Brandon Radzom, Jessica Ranshaw, Xian-Yu Wang
Author-email: armgoyal@iu.edu, bradzom@iu.edu, jranshaw@iu.edu, xwa5@iu.edu
Classifier: License :: OSI Approved :: MIT License
License-File: LICENSE.txt
Requires-Dist: numpy
Requires-Dist: pandas
Requires-Dist: tabulate
Requires-Dist: colorama
Requires-Dist: skyfield
Requires-Dist: astropy
Requires-Dist: astroplan
Requires-Dist: matplotlib
